vloex/__init__.py
vloex/client.py
vloex/exceptions.py
vloex-0.1.5.dist-info/METADATA
vloex-0.1.5.dist-info/WHEEL
vloex-0.1.5.dist-info/top_level.txt
vloex-0.1.5.dist-info/RECORD
