Metadata-Version: 2.1
Name: vloex
Version: 0.1.5
Summary: VLOEX SDK - Video generation as a computing primitive
Home-page: https://api.vloex.com/docs
Author: VLOEX
Author-email: sats@vloex.com
Project-URL: Documentation, https://api.vloex.com/docs
Project-URL: Source, https://github.com/vloex/vloex-python
Project-URL: Bug Reports, https://github.com/vloex/vloex-python/issues
Keywords: vloex video generation api ai avatar
Classifier: Development Status :: 4 - Beta
Classifier: Intended Audience :: Developers
Classifier: License :: OSI Approved :: MIT License
Classifier: Programming Language :: Python :: 3
Classifier: Programming Language :: Python :: 3.8
Classifier: Programming Language :: Python :: 3.9
Classifier: Programming Language :: Python :: 3.10
Classifier: Programming Language :: Python :: 3.11
Classifier: Programming Language :: Python :: 3.12
Requires-Python: >=3.8
Requires-Dist: requests (>=2.25.0)
